aiorecycle/__init__.py
aiorecycle-0.0.2.dist-info/LICENSE
aiorecycle-0.0.2.dist-info/METADATA
aiorecycle-0.0.2.dist-info/WHEEL
aiorecycle-0.0.2.dist-info/top_level.txt
aiorecycle-0.0.2.dist-info/RECORD
