Metadata-Version: 2.1
Name: aiorecycle
Version: 0.0.2
Summary: A decorator to recycle tasks in the event loop
Home-page: https://github.com/mpyatishev/aiorecycle
Author: Maxim Pyatishev
Author-email: mpyatishev@gmail.com
License: UNKNOWN
Platform: UNKNOWN
Classifier: License :: OSI Approved :: Apache Software License
Classifier: Intended Audience :: Developers
Classifier: Programming Language :: Python
Classifier: Programming Language :: Python :: 3
Classifier: Programming Language :: Python :: 3.6
Classifier: Programming Language :: Python :: 3.7
Classifier: Topic :: Software Development :: Libraries
Classifier: Framework :: AsyncIO
Requires-Python: >=3.6
